["```py\npokemon/train/grass/bulbasaur.png\npokemon/train/fire/charmander.png\npokemon/train/water/squirtle.png\n\npokemon/test/grass/ivysaur.png\npokemon/test/fire/charmeleon.png\npokemon/test/water/wartortle.png\n```", "```py\n>>> from datasets import load_dataset\n\n>>> dataset = load_dataset(\"imagefolder\", data_dir=\"/path/to/pokemon\")\n```", "```py\n>>> from datasets import load_dataset\n\n>>> dataset = load_dataset(\"audiofolder\", data_dir=\"/path/to/folder\")\n```", "```py\nfile_name, text\nbulbasaur.png, There is a plant seed on its back right from the day this Pok\u00e9mon is born.\ncharmander.png, It has a preference for hot things.\nsquirtle.png, When it retracts its long neck into its shell, it squirts out water with vigorous force.\n```", "```py\n    >>> from datasets import Dataset\n    >>> def gen():\n    ...     yield {\"pokemon\": \"bulbasaur\", \"type\": \"grass\"}\n    ...     yield {\"pokemon\": \"squirtle\", \"type\": \"water\"}\n    >>> ds = Dataset.from_generator(gen)\n    >>> ds[0]\n    {\"pokemon\": \"bulbasaur\", \"type\": \"grass\"}\n    ```", "```py\n    >>> from datasets import IterableDataset\n    >>> ds = IterableDataset.from_generator(gen)\n    >>> for example in ds:\n    ...     print(example)\n    {\"pokemon\": \"bulbasaur\", \"type\": \"grass\"}\n    {\"pokemon\": \"squirtle\", \"type\": \"water\"}\n    ```", "```py\n    >>> from datasets import Dataset\n    >>> ds = Dataset.from_dict({\"pokemon\": [\"bulbasaur\", \"squirtle\"], \"type\": [\"grass\", \"water\"]})\n    >>> ds[0]\n    {\"pokemon\": \"bulbasaur\", \"type\": \"grass\"}\n    ```", "```py\n    >>> audio_dataset = Dataset.from_dict({\"audio\": [\"path/to/audio_1\", ..., \"path/to/audio_n\"]}).cast_column(\"audio\", Audio())\n    ```"]